sfas/__init__.py
sfas/greedy.py
sfas-1.0.0.dist-info/METADATA
sfas-1.0.0.dist-info/WHEEL
sfas-1.0.0.dist-info/entry_points.txt
sfas-1.0.0.dist-info/license_files/LICENSE
sfas-1.0.0.dist-info/RECORD
