Metadata-Version: 2.1
Name: sfas
Version: 1.0.0
Project-URL: Bug Tracker, https://github.com/ariematsliah-princeton/sfas/issues
Project-URL: Homepage, https://github.com/ariematsliah-princeton/sfas
Author-email: Arie Matsliah <arie.matsliah@gmail.com>
Classifier: License :: OSI Approved :: MIT License
Classifier: Operating System :: OS Independent
Classifier: Programming Language :: Python :: 3
Requires-Python: >=3.6
